SinicValidate/__init__.py
SinicValidate/main.py
SinicValidate-1.0.5.dist-info/DESCRIPTION.rst
SinicValidate-1.0.5.dist-info/METADATA
SinicValidate-1.0.5.dist-info/RECORD
SinicValidate-1.0.5.dist-info/WHEEL
SinicValidate-1.0.5.dist-info/metadata.json
SinicValidate-1.0.5.dist-info/top_level.txt
